mps_to_circuit/__init__.py
mps_to_circuit/imps_to_circuit_exact.py
mps_to_circuit/mps_to_circuit.py
mps_to_circuit/mps_to_circuit_approx.py
mps_to_circuit/mps_to_circuit_exact.py
mps_to_circuit/utils/__init__.py
mps_to_circuit/utils/env_tensor.py
mps_to_circuit/utils/math.py
mps_to_circuit/utils/matrix.py
mps_to_circuit/utils/tensor.py
mps_to_circuit-0.1.2.dist-info/METADATA
mps_to_circuit-0.1.2.dist-info/WHEEL
mps_to_circuit-0.1.2.dist-info/top_level.txt
mps_to_circuit-0.1.2.dist-info/RECORD
