Metadata-Version: 2.2
Name: mps-to-circuit
Version: 0.1.2
Summary: Tool to convert a matrix product state to a Qiskit quantum circuit.
Requires-Python: <3.13,>=3.10
Requires-Dist: qiskit>=1.0.0
Requires-Dist: quimb>=1.10.0
